oarc/__init__.py
oarc/main.py
oarc-0.1.1.dist-info/licenses/LICENSE
oarc-0.1.1.dist-info/METADATA
oarc-0.1.1.dist-info/WHEEL
oarc-0.1.1.dist-info/entry_points.txt
oarc-0.1.1.dist-info/top_level.txt
oarc-0.1.1.dist-info/RECORD
