Metadata-Version: 2.4
Name: oarc
Version: 0.1.1
Summary: OARC Python Package
Author: OARC Team
Requires-Python: <3.12,>=3.10
License-File: LICENSE
Requires-Dist: build
Requires-Dist: setuptools>=45
Requires-Dist: wheel
Requires-Dist: cython>=0.30.0
Requires-Dist: llvmlite>=0.39.0
Requires-Dist: numpy~=2.1.1
Requires-Dist: scipy>=1.13.0
Requires-Dist: librosa>=0.11.0
Requires-Dist: numba>=0.56.0
Requires-Dist: pyaudio>=0.2.13
Requires-Dist: sounddevice>=0.5.1
Requires-Dist: soundfile>=0.12.0
Requires-Dist: PyQt6>=6.4.0
Requires-Dist: llama-index-experimental>=0.5.4
Requires-Dist: llama-index>=0.12.26
Requires-Dist: opencv-python>=4.8.0
Requires-Dist: ollama>=0.4.7
Requires-Dist: transformers>=4.47.0
Requires-Dist: ultralytics>=8.3.102
Requires-Dist: SpeechRecognition>=3.8.1
Requires-Dist: gtts>=2.3.2
Requires-Dist: openai-whisper>=20240930
Requires-Dist: pygame>=2.5.2
Requires-Dist: anyascii>=0.3.0
Requires-Dist: einops>=0.6.0
Requires-Dist: encodec>=0.1.1
Requires-Dist: inflect>=5.6.0
Requires-Dist: num2words>=0.5.14
Requires-Dist: pysbd>=0.3.4
Requires-Dist: tqdm>=4.64.1
Requires-Dist: fsspec[http]>=2023.6.0
Requires-Dist: keyboard>=0.13.5
Requires-Dist: matplotlib>=3.8.4
Requires-Dist: packaging>=23.1
Requires-Dist: pandas>=1.3.0
Requires-Dist: pyyaml>=6.0
Requires-Dist: typing_extensions>=4.10
Requires-Dist: fastapi>=0.68.0
Requires-Dist: gradio>=4.19.0
Requires-Dist: pydantic>=1.8.0
Requires-Dist: python-multipart>=0.0.5
Requires-Dist: requests>=2.26.0
Requires-Dist: uvicorn>=0.15.0
Requires-Dist: websockets>=10.0
Requires-Dist: discord>=2.3.2
Requires-Dist: pyvirtualcam>=0.12.1
Requires-Dist: pywin32>=306; platform_system == "Windows"
Requires-Dist: pytube>=15.0.0
Provides-Extra: dev
Requires-Dist: black; extra == "dev"
Requires-Dist: flake8; extra == "dev"
Requires-Dist: ruff==0.9.1; extra == "dev"
Requires-Dist: pre-commit>=4; extra == "dev"
Requires-Dist: pytest>=8; extra == "dev"
Requires-Dist: coverage[toml]>=7; extra == "dev"
Requires-Dist: sphinx==7.4.7; extra == "dev"
Requires-Dist: furo>=2024.8.6; extra == "dev"
Requires-Dist: sphinx_copybutton>=0.5.2; extra == "dev"
Requires-Dist: twine; extra == "dev"
Requires-Dist: bokeh>=3.0.3; extra == "dev"
Requires-Dist: umap-learn>=0.5.1; extra == "dev"
Dynamic: license-file
